gornilo/__init__.py
gornilo/actions.py
gornilo/generators.py
gornilo/new_actions.py
gornilo/setup_logging.py
gornilo/sub_checker.py
gornilo/utils.py
gornilo/http_clients/__init__.py
gornilo/http_clients/requests_client.py
gornilo/models/__init__.py
gornilo/models/action_names.py
gornilo/models/api_constants.py
gornilo/models/checksystem_request.py
gornilo/models/verdict/__init__.py
gornilo/models/verdict/verdict.py
gornilo/models/verdict/verdict_codes.py
gornilo-1.0.1.dist-info/LICENCE
gornilo-1.0.1.dist-info/METADATA
gornilo-1.0.1.dist-info/WHEEL
gornilo-1.0.1.dist-info/top_level.txt
gornilo-1.0.1.dist-info/RECORD
