Metadata-Version: 2.1
Name: gornilo
Version: 1.0.1
Summary: AD CTFs checker wrapper
Home-page: https://github.com/Hackerdom/Gornilo
Author: rx00
Author-email: rx00@hackerdom.com
Classifier: Programming Language :: Python :: 3
Classifier: License :: OSI Approved :: MIT License
Classifier: Operating System :: OS Independent
Requires-Python: >=3.6
License-File: LICENCE
